sshup/__init__.py
sshup/main.py
sshup-0.0.9.dist-info/licenses/LICENSE
sshup-0.0.9.dist-info/METADATA
sshup-0.0.9.dist-info/WHEEL
sshup-0.0.9.dist-info/entry_points.txt
sshup-0.0.9.dist-info/top_level.txt
sshup-0.0.9.dist-info/RECORD
